<?xml version="1.0"?>
<!--
 Copyright (C) 2004-2005 Laurent Sansonetti

 Alexandria is free software; you can redistribute it and/or
 modify it under the terms of the GNU General Public License as
 published by the Free Software Foundation; either version 2 of the
 License, or (at your option) any later version.

 Alexandria is distributed in the hope that it will be useful,
 but WITHOUT ANY WARRANTY; without even the implied warranty of
 MERCHANTABILITY or FITNESS FOR A PARTICULAR PURPOSE.  See the GNU
 General Public License for more details.

 You should have received a copy of the GNU General Public
 License along with Alexandria; see the file COPYING.  If not,
 write to the Free Software Foundation, Inc., 59 Temple Place - Suite 330,
 Boston, MA 02111-1307, USA.
-->

<ui>
  <popup name="NoLibraryPopup">
    <menuitem action="New"/>
    <menuitem action="NewSmart"/>
  </popup>
  <popup name="SmartLibraryPopup">
    <menuitem action="Properties"/>
    <menuitem action="Rename"/>
    <menuitem action="Export"/>
    <menuitem action="Delete"/>
  </popup>
  <popup name="LibraryPopup">
    <menuitem action="Rename"/>
    <menuitem action="Export"/>
    <menuitem action="Delete"/>
  </popup>
  <popup name="BookPopup">
    <menuitem action="Properties"/>
    <menu action="OnlineInformation"/>
    <separator/>
    <menu action="SetRating">
      <menuitem action="SetRating0"/>
      <menuitem action="SetRating1"/>
      <menuitem action="SetRating2"/>
      <menuitem action="SetRating3"/>
      <menuitem action="SetRating4"/>
      <menuitem action="SetRating5"/>
    </menu>
    <menu action="Move"/>
    <separator/>
    <menuitem action="SelectAll"/>
    <menuitem action="DeselectAll"/>
    <separator/>
    <menu action="ArrangeIcons">
      <menuitem action="ByTitle"/>
      <menuitem action="ByAuthors"/>
      <menuitem action="ByISBN"/>
      <menuitem action="ByPublisher"/>
      <menuitem action="ByEdition"/>
      <menuitem action="ByRating"/>
      <separator/>
      <menuitem action="ReversedOrder"/>
    </menu>
    <separator/>
    <menuitem action="AsIcons"/> 
    <menuitem action="AsList"/> 
    <separator/>
    <menuitem action="Delete"/> 
  </popup>
  <popup name="NoBookPopup">
    <menuitem action="AddBook"/>
    <menuitem action="AddBookManual"/>
    <separator/>
    <menuitem action="SelectAll"/>
    <menuitem action="DeselectAll"/>
    <separator/>
    <menu action="ArrangeIcons">
      <menuitem action="ByTitle"/>
      <menuitem action="ByAuthors"/>
      <menuitem action="ByISBN"/>
      <menuitem action="ByPublisher"/>
      <menuitem action="ByEdition"/>
      <menuitem action="ByRating"/>
      <separator/>
      <menuitem action="ReversedOrder"/>
    </menu>
    <separator/>
    <menuitem action="AsIcons"/> 
    <menuitem action="AsList"/> 
  </popup>
</ui>
